{
  "headers": {
    "vary": "Accept-Encoding",
    "x-amz-request-id": "N4A1Y59HF9TC5KMW",
    "alt-svc": "h3-27=\":443\"; ma=86400, h3-28=\":443\"; ma=86400, h3-29=\":443\"; ma=86400",
    "content-length": "4701",
    "cf-request-id": "090d4d98520000d6dde998f000000001",
    "x-amz-version-id": "vlETyanojfvfUpi7H2xi2qXAOC2xtYQm",
    "x-amz-id-2": "p1Q41wAnkDSWcKX7heCNXazmnMZqlxncQM1ottgwb9OUEJujNFHiInQ5cL0BTZns/ELKcQ5av5Y=",
    "accept-ranges": "bytes",
    "date": "Thu, 25 Mar 2021 23:24:54 GMT",
    "age": "197959",
    "last-modified": "Wed, 20 Jan 2021 05:26:04 GMT",
    "set-cookie": "__cfduid=d1f5c501fc9fc32103ce4c0825f9809b31616714694; expires=Sat, 24-Apr-21 23:24:54 GMT; path=/; domain=.deno.land; HttpOnly; SameSite=Lax; Secure",
    "access-control-allow-origin": "*",
    "content-type": "application/typescript; charset=utf-8",
    "cache-control": "public, max-age=31536000, immutable",
    "expect-ct": "max-age=604800, report-uri=\"https://report-uri.cloudflare.com/cdn-cgi/beacon/expect-ct\"",
    "cf-cache-status": "HIT",
    "server": "cloudflare",
    "etag": "\"fe4d81f74bb47b3f3faf68afd49e4ac5\"",
    "cf-ray": "635be53a1b07d6dd-FRA"
  },
  "url": "https://deno.land/std@0.84.0/textproto/mod.ts"
}